casbin_databases_adapter/__init__.py
casbin_databases_adapter/adapter.py
casbin_databases_adapter-1.6.0.dist-info/licenses/LICENSE
casbin_databases_adapter-1.6.0.dist-info/METADATA
casbin_databases_adapter-1.6.0.dist-info/WHEEL
casbin_databases_adapter-1.6.0.dist-info/top_level.txt
casbin_databases_adapter-1.6.0.dist-info/RECORD
