Metadata-Version: 2.4
Name: casbin_databases_adapter
Version: 1.6.0
Summary: This is an Adapter for PyCasbin that implemented using Databases connection to achieve async process
Home-page: https://github.com/officialpycasbin/casbin-databases-adapter
Author: Isa Setiawan Abdurrazaq
Author-email: isasetiawan@protonmail.com
License: Apache 2.0
Keywords: casbin,asynccasbin,async,databases,casbin-adapter,rbac,access control,abac,acl,permission
Classifier: Programming Language :: Python :: 3.9
Classifier: Programming Language :: Python :: 3.10
Classifier: Programming Language :: Python :: 3.11
Classifier: Programming Language :: Python :: 3.12
Classifier: License :: OSI Approved :: Apache Software License
Classifier: Operating System :: OS Independent
Requires-Python: >=3.3
License-File: LICENSE
Requires-Dist: asynccasbin==1.1.7
Requires-Dist: databases>=0.7.0
Requires-Dist: SQLAlchemy>=1.4.42
Dynamic: author
Dynamic: author-email
Dynamic: classifier
Dynamic: description
Dynamic: description-content-type
Dynamic: home-page
Dynamic: keywords
Dynamic: license
Dynamic: license-file
Dynamic: requires-dist
Dynamic: requires-python
Dynamic: summary
